medpalm/__init__.py
medpalm/attend.py
medpalm/model.py
medpalm/transformer.py
medpalm-0.2.0.dist-info/LICENSE
medpalm-0.2.0.dist-info/WHEEL
medpalm-0.2.0.dist-info/METADATA
medpalm-0.2.0.dist-info/RECORD
